Metadata-Version: 1.0
Name: umltodjango
Version: 1.0.0
Summary: An awesome package to conver UML Diagrams to Django Models
Home-page: https://gitlab.com/albertosanmartinmartinez/umltodjango
Author: Alberto Sanmartin Martinez
Author-email: info@albertosanmartinmartinez.es
License: LICENSE.txt
Platform: UNKNOWN
